{"month_year":"2024\/08","history":{"update_date":"2024\/08\/28 22:21:02","last_update_date":"2024\/08\/28 22:16:02"},"schedule":{"1":{"status":1,"start":"9:00","end":"18:00","close_disp_ja":{},"close_disp_en":{},"event_url":{},"operation_message":{},"price_type":"A","ticket_reserve":1,"ticket_passport":2,"ippan_ninzu":{},"eticket_ninzu":{},"upper_ninzu":{},"eticket_upper_ninzu":{},"in":"#2504","un":"#2700","en":"#1557","eu":"#2000"},"2":{"status":1,"start":"9:00","end":"18:00","close_disp_ja":{},"close_disp_en":{},"event_url":{},"operation_message":{},"price_type":"A","ticket_reserve":1,"ticket_passport":2,"ippan_ninzu":{},"eticket_ninzu":{},"upper_ninzu":{},"eticket_upper_ninzu":{},"in":"#2577","un":"#2750","en":"#1773","eu":"#2000"},"3":{"status":1,"start":"8:30","end":"18:00","close_disp_ja":{},"close_disp_en":{},"event_url":{},"operation_message":{},"price_type":"S","ticket_reserve":1,"ticket_passport":1,"ippan_ninzu":{},"eticket_ninzu":{},"upper_ninzu":{},"eticket_upper_ninzu":{},"in":"#3728","un":"#4000","en":"#2186","eu":"#2400"},"4":{"status":1,"start":"8:30","end":"18:00","close_disp_ja":{},"close_disp_en":{},"event_url":{},"operation_message":{},"price_type":"S","ticket_reserve":1,"ticket_passport":1,"ippan_ninzu":{},"eticket_ninzu":{},"upper_ninzu":{},"eticket_upper_ninzu":{},"in":"#4010","un":"#4250","en":"#2077","eu":"#2200"},"5":{"status":1,"start":"8:30","end":"18:00","close_disp_ja":{},"close_disp_en":{},"event_url":{},"operation_message":{},"price_type":"A","ticket_reserve":1,"ticket_passport":1,"ippan_ninzu":{},"eticket_ninzu":{},"upper_ninzu":{},"eticket_upper_ninzu":{},"in":"#3203","un":"#3400","en":"#1996","eu":"#2200"},"6":{"status":1,"start":"8:30","end":"18:00","close_disp_ja":{},"close_disp_en":{},"event_url":{},"operation_message":{},"price_type":"A","ticket_reserve":1,"ticket_passport":2,"ippan_ninzu":{},"eticket_ninzu":{},"upper_ninzu":{},"eticket_upper_ninzu":{},"in":"#3229","un":"#3500","en":"#1706","eu":"#2000"},"7":{"status":1,"start":"8:30","end":"18:00","close_disp_ja":{},"close_disp_en":{},"event_url":{},"operation_message":{},"price_type":"A","ticket_reserve":1,"ticket_passport":1,"ippan_ninzu":{},"eticket_ninzu":{},"upper_ninzu":{},"eticket_upper_ninzu":{},"in":"#3725","un":"#3900","en":"#2174","eu":"#2400"},"8":{"status":1,"start":"8:30","end":"18:00","close_disp_ja":{},"close_disp_en":{},"event_url":{},"operation_message":{},"price_type":"A","ticket_reserve":1,"ticket_passport":1,"ippan_ninzu":{},"eticket_ninzu":{},"upper_ninzu":{},"eticket_upper_ninzu":{},"in":"#3770","un":"#4000","en":"#2004","eu":"#2200"},"9":{"status":1,"start":"8:30","end":"18:00","close_disp_ja":{},"close_disp_en":{},"event_url":{},"operation_message":{},"price_type":"A","ticket_reserve":1,"ticket_passport":1,"ippan_ninzu":{},"eticket_ninzu":{},"upper_ninzu":{},"eticket_upper_ninzu":{},"in":"#3794","un":"#4100","en":"#2041","eu":"#2200"},"10":{"status":1,"start":"8:30","end":"18:00","close_disp_ja":{},"close_disp_en":{},"event_url":{},"operation_message":{},"price_type":"U","ticket_reserve":1,"ticket_passport":1,"ippan_ninzu":{},"eticket_ninzu":{},"upper_ninzu":{},"eticket_upper_ninzu":{},"in":"#3811","un":"#4100","en":"#2040","eu":"#2100"},"11":{"status":1,"start":"8:30","end":"18:00","close_disp_ja":{},"close_disp_en":{},"event_url":{},"operation_message":{},"price_type":"U","ticket_reserve":1,"ticket_passport":1,"ippan_ninzu":{},"eticket_ninzu":{},"upper_ninzu":{},"eticket_upper_ninzu":{},"in":"#4124","un":"#4300","en":"#2323","eu":"#2500"},"12":{"status":1,"start":"8:30","end":"18:00","close_disp_ja":{},"close_disp_en":{},"event_url":{},"operation_message":{},"price_type":"U","ticket_reserve":1,"ticket_passport":1,"ippan_ninzu":{},"eticket_ninzu":{},"upper_ninzu":{},"eticket_upper_ninzu":{},"in":"#4166","un":"#4500","en":"#2418","eu":"#2500"},"13":{"status":1,"start":"8:30","end":"18:00","close_disp_ja":{},"close_disp_en":{},"event_url":{},"operation_message":{},"price_type":"U","ticket_reserve":1,"ticket_passport":1,"ippan_ninzu":{},"eticket_ninzu":{},"upper_ninzu":{},"eticket_upper_ninzu":{},"in":"#4016","un":"#4300","en":"#2363","eu":"#2600"},"14":{"status":1,"start":"8:30","end":"18:00","close_disp_ja":{},"close_disp_en":{},"event_url":{},"operation_message":{},"price_type":"U","ticket_reserve":1,"ticket_passport":1,"ippan_ninzu":{},"eticket_ninzu":{},"upper_ninzu":{},"eticket_upper_ninzu":{},"in":"#3970","un":"#4300","en":"#2394","eu":"#2600"},"15":{"status":1,"start":"8:30","end":"18:00","close_disp_ja":{},"close_disp_en":{},"event_url":{},"operation_message":{},"price_type":"U","ticket_reserve":1,"ticket_passport":1,"ippan_ninzu":{},"eticket_ninzu":{},"upper_ninzu":{},"eticket_upper_ninzu":{},"in":"#4089","un":"#4500","en":"#2249","eu":"#2400"},"16":{"status":1,"start":"8:30","end":"18:00","close_disp_ja":{},"close_disp_en":{},"event_url":{},"operation_message":{},"price_type":"U","ticket_reserve":2,"ticket_passport":2,"ippan_ninzu":{},"eticket_ninzu":{},"upper_ninzu":{},"eticket_upper_ninzu":{},"in":"#3479","un":"#4000","en":"#1707","eu":"#1900"},"17":{"status":1,"start":"8:30","end":"18:00","close_disp_ja":{},"close_disp_en":{},"event_url":{},"operation_message":{},"price_type":"U","ticket_reserve":1,"ticket_passport":1,"ippan_ninzu":{},"eticket_ninzu":{},"upper_ninzu":{},"eticket_upper_ninzu":{},"in":"#4319","un":"#4700","en":"#1969","eu":"#2050"},"18":{"status":1,"start":"8:30","end":"18:00","close_disp_ja":{},"close_disp_en":{},"event_url":{},"operation_message":{},"price_type":"T","ticket_reserve":1,"ticket_passport":1,"ippan_ninzu":{},"eticket_ninzu":{},"upper_ninzu":{},"eticket_upper_ninzu":{},"in":"#4272","un":"#4600","en":"#1933","eu":"#2100"},"19":{"status":1,"start":"8:30","end":"18:00","close_disp_ja":{},"close_disp_en":{},"event_url":{},"operation_message":{},"price_type":"A","ticket_reserve":1,"ticket_passport":1,"ippan_ninzu":{},"eticket_ninzu":{},"upper_ninzu":{},"eticket_upper_ninzu":{},"in":"#3730","un":"#4000","en":"#2227","eu":"#2400"},"20":{"status":1,"start":"8:30","end":"18:00","close_disp_ja":{},"close_disp_en":{},"event_url":{},"operation_message":{},"price_type":"A","ticket_reserve":1,"ticket_passport":1,"ippan_ninzu":{},"eticket_ninzu":{},"upper_ninzu":{},"eticket_upper_ninzu":{},"in":"#3785","un":"#4100","en":"#2194","eu":"#2400"},"21":{"status":1,"start":"8:30","end":"18:00","close_disp_ja":{},"close_disp_en":{},"event_url":{},"operation_message":{},"price_type":"A","ticket_reserve":1,"ticket_passport":1,"ippan_ninzu":{},"eticket_ninzu":{},"upper_ninzu":{},"eticket_upper_ninzu":{},"in":"#3810","un":"#4000","en":"#2118","eu":"#2300"},"22":{"status":1,"start":"8:30","end":"18:00","close_disp_ja":{},"close_disp_en":{},"event_url":{},"operation_message":{},"price_type":"A","ticket_reserve":1,"ticket_passport":1,"ippan_ninzu":{},"eticket_ninzu":{},"upper_ninzu":{},"eticket_upper_ninzu":{},"in":"#3867","un":"#4200","en":"#1920","eu":"#2100"},"23":{"status":1,"start":"8:30","end":"18:00","close_disp_ja":{},"close_disp_en":{},"event_url":{},"operation_message":{},"price_type":"A","ticket_reserve":1,"ticket_passport":1,"ippan_ninzu":{},"eticket_ninzu":{},"upper_ninzu":{},"eticket_upper_ninzu":{},"in":"#3921","un":"#4200","en":"#1934","eu":"#2100"},"24":{"status":1,"start":"8:30","end":"18:00","close_disp_ja":{},"close_disp_en":{},"event_url":{},"operation_message":{},"price_type":"T","ticket_reserve":1,"ticket_passport":1,"ippan_ninzu":{},"eticket_ninzu":{},"upper_ninzu":{},"eticket_upper_ninzu":{},"in":"#4340","un":"#4600","en":"#1826","eu":"#1950"},"25":{"status":1,"start":"8:30","end":"18:00","close_disp_ja":{},"close_disp_en":{},"event_url":{},"operation_message":{},"price_type":"T","ticket_reserve":1,"ticket_passport":1,"ippan_ninzu":{},"eticket_ninzu":{},"upper_ninzu":{},"eticket_upper_ninzu":{},"in":"#4615","un":"#5000","en":"#1851","eu":"#2000"},"26":{"status":1,"start":"8:30","end":"18:00","close_disp_ja":{},"close_disp_en":{},"event_url":{},"operation_message":{},"price_type":"A","ticket_reserve":1,"ticket_passport":1,"ippan_ninzu":{},"eticket_ninzu":{},"upper_ninzu":{},"eticket_upper_ninzu":{},"in":"#4276","un":"#4650","en":"#1600","eu":"#1700"},"27":{"status":1,"start":"9:00","end":"18:00","close_disp_ja":{},"close_disp_en":{},"event_url":{},"operation_message":{},"price_type":"B","ticket_reserve":1,"ticket_passport":1,"ippan_ninzu":{},"eticket_ninzu":{},"upper_ninzu":{},"eticket_upper_ninzu":{},"in":"#3553","un":"#3850","en":"#1471","eu":"#1550"},"28":{"status":1,"start":"9:00","end":"18:00","close_disp_ja":{},"close_disp_en":{},"event_url":{},"operation_message":{},"price_type":"B","ticket_reserve":1,"ticket_passport":1,"ippan_ninzu":{},"eticket_ninzu":{},"upper_ninzu":{},"eticket_upper_ninzu":{},"in":"#3677","un":"#3900","en":"#1376","eu":"#1500"},"29":{"status":1,"start":"9:00","end":"18:00","close_disp_ja":{},"close_disp_en":{},"event_url":{},"operation_message":{},"price_type":"B","ticket_reserve":0,"ticket_passport":1,"ippan_ninzu":{},"eticket_ninzu":{},"upper_ninzu":{},"eticket_upper_ninzu":{},"in":"#3303","un":"#3300","en":"#1098","eu":"#1100"},"30":{"status":1,"start":"9:00","end":"18:00","close_disp_ja":{},"close_disp_en":{},"event_url":{},"operation_message":{},"price_type":"B","ticket_reserve":0,"ticket_passport":0,"ippan_ninzu":{},"eticket_ninzu":{},"upper_ninzu":{},"eticket_upper_ninzu":{},"in":"#3300","un":"#3300","en":"#1102","eu":"#1100"},"31":{"status":1,"start":"8:30","end":"18:00","close_disp_ja":{},"close_disp_en":{},"event_url":{},"operation_message":{},"price_type":"S","ticket_reserve":1,"ticket_passport":2,"ippan_ninzu":{},"eticket_ninzu":{},"upper_ninzu":{},"eticket_upper_ninzu":{},"in":"#3597","un":"#3600","en":"#1243","eu":"#1500"}},"price":{"price_type":{"U":{"adult_price1":5900,"child_price1":4800,"senior_price1":4800,"adult_price2":3800,"child_price2":3500,"senior_price2":3500,"bg_color":"#e5c7ea","font_color":"#6E6E6E"},"T":{"adult_price1":5600,"child_price1":4500,"senior_price1":4500,"adult_price2":3600,"child_price2":3300,"senior_price2":3300,"bg_color":"#ffd8d8","font_color":"#6E6E6E"},"S":{"adult_price1":5300,"child_price1":4200,"senior_price1":4200,"adult_price2":3400,"child_price2":3100,"senior_price2":3100,"bg_color":"#ffe0b5","font_color":"#6E6E6E"},"A":{"adult_price1":4900,"child_price1":3800,"senior_price1":3800,"adult_price2":3200,"child_price2":2900,"senior_price2":2900,"bg_color":"#f8f0be","font_color":"#6E6E6E"},"B":{"adult_price1":4600,"child_price1":3500,"senior_price1":3500,"adult_price2":3000,"child_price2":2700,"senior_price2":2700,"bg_color":"#c2f2de","font_color":"#6E6E6E"},"C":{"adult_price1":4300,"child_price1":3200,"senior_price1":3200,"adult_price2":2800,"child_price2":2500,"senior_price2":2500,"bg_color":"#c8e7fa","font_color":"#6E6E6E"},"D":{"adult_price1":3900,"child_price1":2800,"senior_price1":2800,"adult_price2":2500,"child_price2":2200,"senior_price2":2200,"bg_color":"#b2d6ff","font_color":"#6E6E6E"}}}}
