{"month_year":"2024\/01","history":{"update_date":"2024\/01\/21 22:16:02","last_update_date":"2024\/01\/21 22:11:01"},"schedule":{"1":{"status":1,"start":"9:00","end":"18:00","close_disp_ja":{},"close_disp_en":{},"event_url":{},"operation_message":{},"price_type":"C","ticket_reserve":1,"ticket_passport":1,"ippan_ninzu":{},"eticket_ninzu":{},"upper_ninzu":{},"eticket_upper_ninzu":{},"in":"#3637","un":"#3800","en":"#1677","eu":"#1800"},"2":{"status":1,"start":"8:30","end":"18:00","close_disp_ja":{},"close_disp_en":{},"event_url":{},"operation_message":{},"price_type":"A","ticket_reserve":1,"ticket_passport":1,"ippan_ninzu":{},"eticket_ninzu":{},"upper_ninzu":{},"eticket_upper_ninzu":{},"in":"#4648","un":"#4900","en":"#1642","eu":"#1800"},"3":{"status":1,"start":"8:30","end":"18:00","close_disp_ja":{},"close_disp_en":{},"event_url":{},"operation_message":{},"price_type":"A","ticket_reserve":1,"ticket_passport":1,"ippan_ninzu":{},"eticket_ninzu":{},"upper_ninzu":{},"eticket_upper_ninzu":{},"in":"#4586","un":"#4900","en":"#1642","eu":"#1800"},"4":{"status":1,"start":"9:00","end":"18:00","close_disp_ja":{},"close_disp_en":{},"event_url":{},"operation_message":{},"price_type":"B","ticket_reserve":1,"ticket_passport":1,"ippan_ninzu":{},"eticket_ninzu":{},"upper_ninzu":{},"eticket_upper_ninzu":{},"in":"#3716","un":"#3900","en":"#1673","eu":"#1800"},"5":{"status":1,"start":"9:00","end":"18:00","close_disp_ja":{},"close_disp_en":{},"event_url":{},"operation_message":{},"price_type":"B","ticket_reserve":1,"ticket_passport":1,"ippan_ninzu":{},"eticket_ninzu":{},"upper_ninzu":{},"eticket_upper_ninzu":{},"in":"#3653","un":"#3750","en":"#1675","eu":"#1800"},"6":{"status":1,"start":"8:30","end":"18:00","close_disp_ja":{},"close_disp_en":{},"event_url":{},"operation_message":{},"price_type":"A","ticket_reserve":1,"ticket_passport":2,"ippan_ninzu":{},"eticket_ninzu":{},"upper_ninzu":{},"eticket_upper_ninzu":{},"in":"#4493","un":"#4700","en":"#1433","eu":"#1600"},"7":{"status":1,"start":"8:30","end":"18:00","close_disp_ja":{},"close_disp_en":{},"event_url":{},"operation_message":{},"price_type":"S","ticket_reserve":1,"ticket_passport":1,"ippan_ninzu":{},"eticket_ninzu":{},"upper_ninzu":{},"eticket_upper_ninzu":{},"in":"#4783","un":"#5100","en":"#1635","eu":"#1800"},"8":{"status":1,"start":"8:30","end":"18:00","close_disp_ja":{},"close_disp_en":{},"event_url":{},"operation_message":{},"price_type":"B","ticket_reserve":1,"ticket_passport":2,"ippan_ninzu":{},"eticket_ninzu":{},"upper_ninzu":{},"eticket_upper_ninzu":{},"in":"#4467","un":"#4650","en":"#1347","eu":"#1550"},"9":{"status":1,"start":"10:00","end":"17:00","close_disp_ja":{},"close_disp_en":{},"event_url":{},"operation_message":{},"price_type":"D","ticket_reserve":2,"ticket_passport":2,"ippan_ninzu":{},"eticket_ninzu":{},"upper_ninzu":{},"eticket_upper_ninzu":{},"in":"#1777","un":"#2300","en":"#786","eu":"#1500"},"10":{"status":0,"start":{},"end":{},"close_disp_ja":"\u672C\u65E5\u306F\u4F11\u9928\u65E5\u3067\u3059\u3002","close_disp_en":"Day off Today.","event_url":{},"operation_message":{},"price_type":{},"ticket_reserve":{},"ticket_passport":{},"ippan_ninzu":{},"eticket_ninzu":{},"upper_ninzu":{},"eticket_upper_ninzu":{}},"11":{"status":0,"start":{},"end":{},"close_disp_ja":"\u672C\u65E5\u306F\u4F11\u9928\u65E5\u3067\u3059\u3002","close_disp_en":"Day off Today.","event_url":{},"operation_message":{},"price_type":{},"ticket_reserve":{},"ticket_passport":{},"ippan_ninzu":{},"eticket_ninzu":{},"upper_ninzu":{},"eticket_upper_ninzu":{}},"12":{"status":1,"start":"9:30","end":"17:00","close_disp_ja":{},"close_disp_en":{},"event_url":{},"operation_message":{},"price_type":"D","ticket_reserve":2,"ticket_passport":2,"ippan_ninzu":{},"eticket_ninzu":{},"upper_ninzu":{},"eticket_upper_ninzu":{},"in":"#2109","un":"#2900","en":"#770","eu":"#1500"},"13":{"status":1,"start":"8:30","end":"18:00","close_disp_ja":{},"close_disp_en":{},"event_url":{},"operation_message":{},"price_type":"A","ticket_reserve":1,"ticket_passport":2,"ippan_ninzu":{},"eticket_ninzu":{},"upper_ninzu":{},"eticket_upper_ninzu":{},"in":"#4887","un":"#5000","en":"#1395","eu":"#1600"},"14":{"status":1,"start":"8:30","end":"18:00","close_disp_ja":{},"close_disp_en":{},"event_url":{},"operation_message":{},"price_type":"A","ticket_reserve":1,"ticket_passport":2,"ippan_ninzu":{},"eticket_ninzu":{},"upper_ninzu":{},"eticket_upper_ninzu":{},"in":"#5025","un":"#5200","en":"#1201","eu":"#1400"},"15":{"status":1,"start":"10:00","end":"17:00","close_disp_ja":{},"close_disp_en":{},"event_url":{},"operation_message":{},"price_type":"D","ticket_reserve":1,"ticket_passport":2,"ippan_ninzu":{},"eticket_ninzu":{},"upper_ninzu":{},"eticket_upper_ninzu":{},"in":"#2087","un":"#2300","en":"#704","eu":"#1500"},"16":{"status":1,"start":"10:00","end":"17:00","close_disp_ja":{},"close_disp_en":{},"event_url":{},"operation_message":{},"price_type":"D","ticket_reserve":1,"ticket_passport":2,"ippan_ninzu":{},"eticket_ninzu":{},"upper_ninzu":{},"eticket_upper_ninzu":{},"in":"#2088","un":"#2300","en":"#737","eu":"#1500"},"17":{"status":0,"start":{},"end":{},"close_disp_ja":"\u672C\u65E5\u306F\u4F11\u9928\u65E5\u3067\u3059\u3002","close_disp_en":"Day off Today.","event_url":{},"operation_message":{},"price_type":{},"ticket_reserve":{},"ticket_passport":{},"ippan_ninzu":{},"eticket_ninzu":{},"upper_ninzu":{},"eticket_upper_ninzu":{}},"18":{"status":1,"start":"9:30","end":"17:00","close_disp_ja":{},"close_disp_en":{},"event_url":{},"operation_message":{},"price_type":"C","ticket_reserve":1,"ticket_passport":2,"ippan_ninzu":{},"eticket_ninzu":{},"upper_ninzu":{},"eticket_upper_ninzu":{},"in":"#2591","un":"#2700","en":"#561","eu":"#1500"},"19":{"status":1,"start":"9:30","end":"17:00","close_disp_ja":{},"close_disp_en":{},"event_url":{},"operation_message":{},"price_type":"D","ticket_reserve":2,"ticket_passport":2,"ippan_ninzu":{},"eticket_ninzu":{},"upper_ninzu":{},"eticket_upper_ninzu":{},"in":"#2539","un":"#2900","en":"#855","eu":"#1500"},"20":{"status":1,"start":"8:30","end":"18:00","close_disp_ja":{},"close_disp_en":{},"event_url":{},"operation_message":{},"price_type":"A","ticket_reserve":1,"ticket_passport":1,"ippan_ninzu":{},"eticket_ninzu":{},"upper_ninzu":{},"eticket_upper_ninzu":{},"in":"#5493","un":"#5700","en":"#1388","eu":"#1500"},"21":{"status":1,"start":"8:30","end":"18:00","close_disp_ja":{},"close_disp_en":{},"event_url":{},"operation_message":{},"price_type":"A","ticket_reserve":1,"ticket_passport":1,"ippan_ninzu":{},"eticket_ninzu":{},"upper_ninzu":{},"eticket_upper_ninzu":{},"in":"#5625","un":"#5700","en":"#1318","eu":"#1450"},"22":{"status":1,"start":"9:30","end":"17:00","close_disp_ja":{},"close_disp_en":{},"event_url":{},"operation_message":{},"price_type":"C","ticket_reserve":2,"ticket_passport":2,"ippan_ninzu":{},"eticket_ninzu":{},"upper_ninzu":{},"eticket_upper_ninzu":{},"in":"#2625","un":"#3000","en":"#587","eu":"#1400"},"23":{"status":1,"start":"10:00","end":"17:00","close_disp_ja":{},"close_disp_en":{},"event_url":{},"operation_message":{},"price_type":"C","ticket_reserve":2,"ticket_passport":2,"ippan_ninzu":{},"eticket_ninzu":{},"upper_ninzu":{},"eticket_upper_ninzu":{},"in":"#1707","un":"#2400","en":"#340","eu":"#1400"},"24":{"status":0,"start":{},"end":{},"close_disp_ja":"\u672C\u65E5\u306F\u4F11\u9928\u65E5\u3067\u3059\u3002","close_disp_en":"Day off Today.","event_url":{},"operation_message":{},"price_type":{},"ticket_reserve":{},"ticket_passport":{},"ippan_ninzu":{},"eticket_ninzu":{},"upper_ninzu":{},"eticket_upper_ninzu":{}},"25":{"status":0,"start":{},"end":{},"close_disp_ja":"\u672C\u65E5\u306F\u4F11\u9928\u65E5\u3067\u3059\u3002","close_disp_en":"Day off Today.","event_url":{},"operation_message":{},"price_type":{},"ticket_reserve":{},"ticket_passport":{},"ippan_ninzu":{},"eticket_ninzu":{},"upper_ninzu":{},"eticket_upper_ninzu":{}},"26":{"status":1,"start":"9:30","end":"17:00","close_disp_ja":{},"close_disp_en":{},"event_url":{},"operation_message":{},"price_type":"C","ticket_reserve":2,"ticket_passport":2,"ippan_ninzu":{},"eticket_ninzu":{},"upper_ninzu":{},"eticket_upper_ninzu":{},"in":"#1874","un":"#3000","en":"#345","eu":"#1400"},"27":{"status":1,"start":"8:30","end":"18:00","close_disp_ja":{},"close_disp_en":{},"event_url":{},"operation_message":{},"price_type":"A","ticket_reserve":0,"ticket_passport":2,"ippan_ninzu":{},"eticket_ninzu":{},"upper_ninzu":{},"eticket_upper_ninzu":{},"in":"#5101","un":"#5100","en":"#691","eu":"#900"},"28":{"status":1,"start":"8:30","end":"18:00","close_disp_ja":{},"close_disp_en":{},"event_url":{},"operation_message":{},"price_type":"A","ticket_reserve":0,"ticket_passport":2,"ippan_ninzu":{},"eticket_ninzu":{},"upper_ninzu":{},"eticket_upper_ninzu":{},"in":"#5101","un":"#5100","en":"#558","eu":"#900"},"29":{"status":1,"start":"9:30","end":"17:00","close_disp_ja":{},"close_disp_en":{},"event_url":{},"operation_message":{},"price_type":"C","ticket_reserve":2,"ticket_passport":2,"ippan_ninzu":{},"eticket_ninzu":{},"upper_ninzu":{},"eticket_upper_ninzu":{},"in":"#1559","un":"#3000","en":"#253","eu":"#1400"},"30":{"status":1,"start":"9:30","end":"17:00","close_disp_ja":{},"close_disp_en":{},"event_url":{},"operation_message":{},"price_type":"C","ticket_reserve":2,"ticket_passport":2,"ippan_ninzu":{},"eticket_ninzu":{},"upper_ninzu":{},"eticket_upper_ninzu":{},"in":"#1138","un":"#3000","en":"#156","eu":"#1400"},"31":{"status":1,"start":"9:30","end":"17:00","close_disp_ja":{},"close_disp_en":{},"event_url":{},"operation_message":{},"price_type":"C","ticket_reserve":2,"ticket_passport":2,"ippan_ninzu":{},"eticket_ninzu":{},"upper_ninzu":{},"eticket_upper_ninzu":{},"in":"#1168","un":"#3000","en":"#191","eu":"#1400"}},"price":{"price_type":{"S":{"adult_price1":5300,"child_price1":4200,"senior_price1":4200,"adult_price2":3400,"child_price2":3100,"senior_price2":3100,"bg_color":"#D0B0FF","font_color":"#6E6E6E"},"A":{"adult_price1":4900,"child_price1":3800,"senior_price1":3800,"adult_price2":3200,"child_price2":2900,"senior_price2":2900,"bg_color":"#D6D0FC","font_color":"#6E6E6E"},"B":{"adult_price1":4600,"child_price1":3500,"senior_price1":3500,"adult_price2":3000,"child_price2":2700,"senior_price2":2700,"bg_color":"#FFBED2","font_color":"#6E6E6E"},"C":{"adult_price1":4300,"child_price1":3200,"senior_price1":3200,"adult_price2":2800,"child_price2":2500,"senior_price2":2500,"bg_color":"#FFD6AD","font_color":"#6E6E6E"},"D":{"adult_price1":3900,"child_price1":2800,"senior_price1":2800,"adult_price2":2500,"child_price2":2200,"senior_price2":2200,"bg_color":"#FFF1A7","font_color":"#6E6E6E"},"E":{"adult_price1":3600,"child_price1":2500,"senior_price1":2500,"adult_price2":2400,"child_price2":2200,"senior_price2":2200,"bg_color":"#ACF2CB","font_color":"#6E6E6E"}}}}
